yami/__init__.py
yami/__main__.py
yami/_cli.py
yami/args.py
yami/bot.py
yami/checks.py
yami/commands.py
yami/context.py
yami/converters.py
yami/events.py
yami/exceptions.py
yami/modules.py
yami/py.typed
yami/utils/__init__.py
yami/utils/this.py
yami/utils/types.py
yami-0.4.1.dist-info/entry_points.txt
yami-0.4.1.dist-info/LICENSE
yami-0.4.1.dist-info/WHEEL
yami-0.4.1.dist-info/METADATA
yami-0.4.1.dist-info/RECORD
