Metadata-Version: 2.1
Name: yami
Version: 0.4.1
Summary: A command handler that complements Hikari.
Home-page: https://github.com/Jonxslays/Yami
License: GPL-3.0-or-later
Author: Jonxslays
Requires-Python: >=3.8,<3.11
Classifier: Development Status :: 3 - Alpha
Classifier: Framework :: AsyncIO
Classifier: Intended Audience :: Developers
Classifier: License :: OSI Approved :: GNU General Public License v3 (GPLv3)
Classifier: License :: OSI Approved :: GNU General Public License v3 or later (GPLv3+)
Classifier: Operating System :: OS Independent
Classifier: Programming Language :: Python :: 3
Classifier: Programming Language :: Python :: 3 :: Only
Classifier: Programming Language :: Python :: 3.10
Classifier: Programming Language :: Python :: 3.8
Classifier: Programming Language :: Python :: 3.9
Classifier: Topic :: Software Development :: Libraries
Classifier: Topic :: Software Development :: Libraries :: Python Modules
Classifier: Typing :: Typed
Provides-Extra: speedups
Requires-Dist: aiodns (>=3.0,<4.0); extra == "speedups"
Requires-Dist: brotli (>=1.0,<2.0); extra == "speedups"
Requires-Dist: cchardet (>=2.1,<3.0); extra == "speedups"
Requires-Dist: ciso8601 (>=2.2,<3.0); extra == "speedups"
Requires-Dist: hikari (==2.0.0.dev108)
Project-URL: Documentation, https://jonxslays.github.io/Yami
Project-URL: Repository, https://github.com/Jonxslays/Yami
